{
  "meta": {
    "version": "1.0",
    "buildDate": "2025-08-06T12:40:33.925Z",
    "entryCount": 1293,
    "totalProcessed": 1296,
    "buildTimeMs": 5,
    "description": "Multi-word entries for PhraseMachine v2 compound detection",
    "source": "Expanded from curated WordNet-style patterns"
  },
  "entries": [
    "afternoon tea",
    "american beef",
    "american bread",
    "american burger",
    "american cake",
    "american cheese",
    "american chicken",
    "american cookie",
    "american dessert",
    "american dish",
    "american fish",
    "american food",
    "american fruit",
    "american meal",
    "american milk",
    "american pasta",
    "american pizza",
    "american pork",
    "american salad",
    "american sandwich",
    "american snack",
    "american soup",
    "american sushi",
    "american taco",
    "american vegetable",
    "amusement park",
    "app for music",
    "automatic application",
    "automatic camera",
    "automatic computer",
    "automatic device",
    "automatic gadget",
    "automatic machine",
    "automatic network",
    "automatic phone",
    "automatic player",
    "automatic service",
    "automatic software",
    "automatic system",
    "automatic tool",
    "bath room",
    "battery application",
    "battery camera",
    "battery computer",
    "battery device",
    "battery gadget",
    "battery machine",
    "battery network",
    "battery phone",
    "battery player",
    "battery service",
    "battery software",
    "battery system",
    "battery tool",
    "bed room",
    "bed time",
    "big airport",
    "big avenue",
    "big bar",
    "big building",
    "big cafe",
    "big center",
    "big hospital",
    "big house",
    "big library",
    "big mall",
    "big museum",
    "big office",
    "big park",
    "big restaurant",
    "big school",
    "big shop",
    "big square",
    "big station",
    "big store",
    "big street",
    "big theater",
    "birthday party",
    "block party",
    "board game",
    "book on shelf",
    "book store",
    "break time",
    "bus station",
    "bus train",
    "business trip",
    "busy airport",
    "busy avenue",
    "busy bar",
    "busy building",
    "busy cafe",
    "busy center",
    "busy hospital",
    "busy house",
    "busy library",
    "busy mall",
    "busy museum",
    "busy office",
    "busy park",
    "busy restaurant",
    "busy school",
    "busy shop",
    "busy square",
    "busy station",
    "busy store",
    "busy street",
    "busy theater",
    "cable television",
    "camping trip",
    "car in garage",
    "car with radio",
    "cell phone",
    "chinese beef",
    "chinese bread",
    "chinese burger",
    "chinese cake",
    "chinese cheese",
    "chinese chicken",
    "chinese cookie",
    "chinese dessert",
    "chinese dish",
    "chinese fish",
    "chinese food",
    "chinese fruit",
    "chinese meal",
    "chinese milk",
    "chinese pasta",
    "chinese pizza",
    "chinese pork",
    "chinese salad",
    "chinese sandwich",
    "chinese snack",
    "chinese soup",
    "chinese sushi",
    "chinese taco",
    "chinese vegetable",
    "class room",
    "coffee shop",
    "cold beef",
    "cold bread",
    "cold burger",
    "cold cake",
    "cold cheese",
    "cold chicken",
    "cold cookie",
    "cold dessert",
    "cold dish",
    "cold fish",
    "cold food",
    "cold fruit",
    "cold meal",
    "cold milk",
    "cold pasta",
    "cold pizza",
    "cold pork",
    "cold salad",
    "cold sandwich",
    "cold snack",
    "cold soup",
    "cold sushi",
    "cold taco",
    "cold vegetable",
    "comfort food",
    "cook bike",
    "cook book",
    "cook car",
    "cook computer",
    "cook food",
    "cook game",
    "cook guitar",
    "cook movie",
    "cook music",
    "cook phone",
    "cook piano",
    "cook radio",
    "cook sport",
    "cook television",
    "credit card",
    "dance bike",
    "dance book",
    "dance car",
    "dance computer",
    "dance food",
    "dance game",
    "dance guitar",
    "dance movie",
    "dance music",
    "dance phone",
    "dance piano",
    "dance radio",
    "dance sport",
    "dance television",
    "department store",
    "desktop computer",
    "digital application",
    "digital camera",
    "digital computer",
    "digital device",
    "digital gadget",
    "digital machine",
    "digital network",
    "digital phone",
    "digital player",
    "digital service",
    "digital software",
    "digital system",
    "digital tool",
    "dining room",
    "dinner party",
    "downtown airport",
    "downtown avenue",
    "downtown bar",
    "downtown building",
    "downtown cafe",
    "downtown center",
    "downtown hospital",
    "downtown house",
    "downtown library",
    "downtown mall",
    "downtown museum",
    "downtown office",
    "downtown park",
    "downtown restaurant",
    "downtown school",
    "downtown shop",
    "downtown square",
    "downtown station",
    "downtown store",
    "downtown street",
    "downtown theater",
    "drink bike",
    "drink book",
    "drink car",
    "drink computer",
    "drink food",
    "drink game",
    "drink guitar",
    "drink movie",
    "drink music",
    "drink phone",
    "drink piano",
    "drink radio",
    "drink sport",
    "drink television",
    "drive bike",
    "drive book",
    "drive car",
    "drive computer",
    "drive food",
    "drive game",
    "drive guitar",
    "drive movie",
    "drive music",
    "drive phone",
    "drive piano",
    "drive radio",
    "drive sport",
    "drive television",
    "eat bike",
    "eat book",
    "eat car",
    "eat computer",
    "eat food",
    "eat game",
    "eat guitar",
    "eat movie",
    "eat music",
    "eat phone",
    "eat piano",
    "eat radio",
    "eat sport",
    "eat television",
    "electric application",
    "electric camera",
    "electric computer",
    "electric device",
    "electric gadget",
    "electric machine",
    "electric network",
    "electric phone",
    "electric player",
    "electric service",
    "electric software",
    "electric system",
    "electric tool",
    "electronic application",
    "electronic camera",
    "electronic computer",
    "electronic device",
    "electronic gadget",
    "electronic machine",
    "electronic network",
    "electronic phone",
    "electronic player",
    "electronic service",
    "electronic software",
    "electronic system",
    "electronic tool",
    "family trip",
    "fast beef",
    "fast bread",
    "fast burger",
    "fast cake",
    "fast cheese",
    "fast chicken",
    "fast cookie",
    "fast dessert",
    "fast dish",
    "fast fish",
    "fast food",
    "fast fruit",
    "fast meal",
    "fast milk",
    "fast pasta",
    "fast pizza",
    "fast pork",
    "fast salad",
    "fast sandwich",
    "fast snack",
    "fast soup",
    "fast sushi",
    "fast taco",
    "fast vegetable",
    "field goal",
    "fire station",
    "food on table",
    "free throw",
    "french beef",
    "french bread",
    "french burger",
    "french cake",
    "french cheese",
    "french chicken",
    "french cookie",
    "french dessert",
    "french dish",
    "french fish",
    "french food",
    "french fries",
    "french fruit",
    "french meal",
    "french milk",
    "french pasta",
    "french pizza",
    "french pork",
    "french salad",
    "french sandwich",
    "french snack",
    "french soup",
    "french sushi",
    "french taco",
    "french vegetable",
    "fresh beef",
    "fresh bread",
    "fresh burger",
    "fresh cake",
    "fresh cheese",
    "fresh chicken",
    "fresh cookie",
    "fresh dessert",
    "fresh dish",
    "fresh fish",
    "fresh food",
    "fresh fruit",
    "fresh meal",
    "fresh milk",
    "fresh pasta",
    "fresh pizza",
    "fresh pork",
    "fresh salad",
    "fresh sandwich",
    "fresh snack",
    "fresh soup",
    "fresh sushi",
    "fresh taco",
    "fresh vegetable",
    "frozen beef",
    "frozen bread",
    "frozen burger",
    "frozen cake",
    "frozen cheese",
    "frozen chicken",
    "frozen cookie",
    "frozen dessert",
    "frozen dish",
    "frozen fish",
    "frozen food",
    "frozen fruit",
    "frozen meal",
    "frozen milk",
    "frozen pasta",
    "frozen pizza",
    "frozen pork",
    "frozen salad",
    "frozen sandwich",
    "frozen snack",
    "frozen soup",
    "frozen sushi",
    "frozen taco",
    "frozen vegetable",
    "game console",
    "game for kids",
    "game show",
    "gas station",
    "grocery store",
    "happy hour",
    "health food",
    "healthy beef",
    "healthy bread",
    "healthy burger",
    "healthy cake",
    "healthy cheese",
    "healthy chicken",
    "healthy cookie",
    "healthy dessert",
    "healthy dish",
    "healthy fish",
    "healthy food",
    "healthy fruit",
    "healthy meal",
    "healthy milk",
    "healthy pasta",
    "healthy pizza",
    "healthy pork",
    "healthy salad",
    "healthy sandwich",
    "healthy snack",
    "healthy soup",
    "healthy sushi",
    "healthy taco",
    "healthy vegetable",
    "high school",
    "historic airport",
    "historic avenue",
    "historic bar",
    "historic building",
    "historic cafe",
    "historic center",
    "historic hospital",
    "historic house",
    "historic library",
    "historic mall",
    "historic museum",
    "historic office",
    "historic park",
    "historic restaurant",
    "historic school",
    "historic shop",
    "historic square",
    "historic station",
    "historic store",
    "historic street",
    "historic theater",
    "home beef",
    "home bread",
    "home burger",
    "home cake",
    "home cheese",
    "home chicken",
    "home cookie",
    "home dessert",
    "home dish",
    "home fish",
    "home food",
    "home fruit",
    "home meal",
    "home milk",
    "home pasta",
    "home pizza",
    "home pork",
    "home run",
    "home salad",
    "home sandwich",
    "home snack",
    "home soup",
    "home sushi",
    "home taco",
    "home vegetable",
    "hot beef",
    "hot bread",
    "hot burger",
    "hot cake",
    "hot cheese",
    "hot chicken",
    "hot cookie",
    "hot dessert",
    "hot dish",
    "hot dog",
    "hot fish",
    "hot food",
    "hot fruit",
    "hot meal",
    "hot milk",
    "hot pasta",
    "hot pizza",
    "hot pork",
    "hot salad",
    "hot sandwich",
    "hot snack",
    "hot soup",
    "hot sushi",
    "hot taco",
    "hot vegetable",
    "house in suburbs",
    "house party",
    "house with pool",
    "ice cream",
    "indian beef",
    "indian bread",
    "indian burger",
    "indian cake",
    "indian cheese",
    "indian chicken",
    "indian cookie",
    "indian dessert",
    "indian dish",
    "indian fish",
    "indian food",
    "indian fruit",
    "indian meal",
    "indian milk",
    "indian pasta",
    "indian pizza",
    "indian pork",
    "indian salad",
    "indian sandwich",
    "indian snack",
    "indian soup",
    "indian sushi",
    "indian taco",
    "indian vegetable",
    "indoor airport",
    "indoor avenue",
    "indoor bar",
    "indoor building",
    "indoor cafe",
    "indoor center",
    "indoor hospital",
    "indoor house",
    "indoor library",
    "indoor mall",
    "indoor museum",
    "indoor office",
    "indoor park",
    "indoor restaurant",
    "indoor school",
    "indoor shop",
    "indoor square",
    "indoor station",
    "indoor store",
    "indoor street",
    "indoor theater",
    "italian beef",
    "italian bread",
    "italian burger",
    "italian cake",
    "italian cheese",
    "italian chicken",
    "italian cookie",
    "italian dessert",
    "italian dish",
    "italian fish",
    "italian food",
    "italian fruit",
    "italian meal",
    "italian milk",
    "italian pasta",
    "italian pizza",
    "italian pork",
    "italian salad",
    "italian sandwich",
    "italian snack",
    "italian soup",
    "italian sushi",
    "italian taco",
    "italian vegetable",
    "junk beef",
    "junk bread",
    "junk burger",
    "junk cake",
    "junk cheese",
    "junk chicken",
    "junk cookie",
    "junk dessert",
    "junk dish",
    "junk fish",
    "junk food",
    "junk fruit",
    "junk meal",
    "junk milk",
    "junk pasta",
    "junk pizza",
    "junk pork",
    "junk salad",
    "junk sandwich",
    "junk snack",
    "junk soup",
    "junk sushi",
    "junk taco",
    "junk vegetable",
    "laptop computer",
    "laptop with battery",
    "listen bike",
    "listen book",
    "listen car",
    "listen computer",
    "listen food",
    "listen game",
    "listen guitar",
    "listen movie",
    "listen music",
    "listen phone",
    "listen piano",
    "listen radio",
    "listen sport",
    "listen television",
    "living room",
    "local airport",
    "local avenue",
    "local bar",
    "local building",
    "local cafe",
    "local center",
    "local hospital",
    "local house",
    "local library",
    "local mall",
    "local museum",
    "local office",
    "local park",
    "local restaurant",
    "local school",
    "local shop",
    "local square",
    "local station",
    "local store",
    "local street",
    "local theater",
    "lunch break",
    "manual application",
    "manual camera",
    "manual computer",
    "manual device",
    "manual gadget",
    "manual machine",
    "manual network",
    "manual phone",
    "manual player",
    "manual service",
    "manual software",
    "manual system",
    "manual tool",
    "mass media",
    "meal time",
    "mexican beef",
    "mexican bread",
    "mexican burger",
    "mexican cake",
    "mexican cheese",
    "mexican chicken",
    "mexican cookie",
    "mexican dessert",
    "mexican dish",
    "mexican fish",
    "mexican food",
    "mexican fruit",
    "mexican meal",
    "mexican milk",
    "mexican pasta",
    "mexican pizza",
    "mexican pork",
    "mexican salad",
    "mexican sandwich",
    "mexican snack",
    "mexican soup",
    "mexican sushi",
    "mexican taco",
    "mexican vegetable",
    "mobile application",
    "mobile camera",
    "mobile computer",
    "mobile device",
    "mobile gadget",
    "mobile machine",
    "mobile network",
    "mobile phone",
    "mobile player",
    "mobile service",
    "mobile software",
    "mobile system",
    "mobile tool",
    "modern airport",
    "modern avenue",
    "modern bar",
    "modern building",
    "modern cafe",
    "modern center",
    "modern hospital",
    "modern house",
    "modern library",
    "modern mall",
    "modern museum",
    "modern office",
    "modern park",
    "modern restaurant",
    "modern school",
    "modern shop",
    "modern square",
    "modern station",
    "modern store",
    "modern street",
    "modern theater",
    "morning afternoon",
    "morning coffee",
    "movie theater",
    "music store",
    "national park",
    "new airport",
    "new avenue",
    "new bar",
    "new building",
    "new cafe",
    "new center",
    "new hospital",
    "new house",
    "new library",
    "new mall",
    "new museum",
    "new office",
    "new park",
    "new restaurant",
    "new school",
    "new shop",
    "new square",
    "new station",
    "new store",
    "new street",
    "new theater",
    "news media",
    "old airport",
    "old avenue",
    "old bar",
    "old building",
    "old cafe",
    "old center",
    "old hospital",
    "old house",
    "old library",
    "old mall",
    "old museum",
    "old office",
    "old park",
    "old restaurant",
    "old school",
    "old shop",
    "old square",
    "old station",
    "old store",
    "old street",
    "old theater",
    "organic beef",
    "organic bread",
    "organic burger",
    "organic cake",
    "organic cheese",
    "organic chicken",
    "organic cookie",
    "organic dessert",
    "organic dish",
    "organic fish",
    "organic food",
    "organic fruit",
    "organic meal",
    "organic milk",
    "organic pasta",
    "organic pizza",
    "organic pork",
    "organic salad",
    "organic sandwich",
    "organic snack",
    "organic soup",
    "organic sushi",
    "organic taco",
    "organic vegetable",
    "outdoor airport",
    "outdoor avenue",
    "outdoor bar",
    "outdoor building",
    "outdoor cafe",
    "outdoor center",
    "outdoor hospital",
    "outdoor house",
    "outdoor library",
    "outdoor mall",
    "outdoor museum",
    "outdoor office",
    "outdoor park",
    "outdoor restaurant",
    "outdoor school",
    "outdoor shop",
    "outdoor square",
    "outdoor station",
    "outdoor store",
    "outdoor street",
    "outdoor theater",
    "parking lot",
    "phone computer",
    "phone with camera",
    "play bike",
    "play book",
    "play car",
    "play computer",
    "play food",
    "play game",
    "play guitar",
    "play movie",
    "play music",
    "play phone",
    "play piano",
    "play radio",
    "play sport",
    "play television",
    "police station",
    "pool party",
    "pop music",
    "portable application",
    "portable camera",
    "portable computer",
    "portable device",
    "portable gadget",
    "portable machine",
    "portable network",
    "portable phone",
    "portable player",
    "portable service",
    "portable software",
    "portable system",
    "portable tool",
    "post office",
    "prime time",
    "private airport",
    "private avenue",
    "private bar",
    "private building",
    "private cafe",
    "private center",
    "private hospital",
    "private house",
    "private library",
    "private mall",
    "private museum",
    "private office",
    "private park",
    "private restaurant",
    "private school",
    "private shop",
    "private square",
    "private station",
    "private store",
    "private street",
    "private theater",
    "public airport",
    "public avenue",
    "public bar",
    "public building",
    "public cafe",
    "public center",
    "public hospital",
    "public house",
    "public library",
    "public mall",
    "public museum",
    "public office",
    "public park",
    "public restaurant",
    "public school",
    "public shop",
    "public square",
    "public station",
    "public store",
    "public street",
    "public theater",
    "quiet airport",
    "quiet avenue",
    "quiet bar",
    "quiet building",
    "quiet cafe",
    "quiet center",
    "quiet hospital",
    "quiet house",
    "quiet library",
    "quiet mall",
    "quiet museum",
    "quiet office",
    "quiet park",
    "quiet restaurant",
    "quiet school",
    "quiet shop",
    "quiet square",
    "quiet station",
    "quiet store",
    "quiet street",
    "quiet theater",
    "read bike",
    "read book",
    "read car",
    "read computer",
    "read food",
    "read game",
    "read guitar",
    "read movie",
    "read music",
    "read phone",
    "read piano",
    "read radio",
    "read sport",
    "read television",
    "reality show",
    "rechargeable application",
    "rechargeable camera",
    "rechargeable computer",
    "rechargeable device",
    "rechargeable gadget",
    "rechargeable machine",
    "rechargeable network",
    "rechargeable phone",
    "rechargeable player",
    "rechargeable service",
    "rechargeable software",
    "rechargeable system",
    "rechargeable tool",
    "restaurant beef",
    "restaurant bread",
    "restaurant burger",
    "restaurant cake",
    "restaurant cheese",
    "restaurant chicken",
    "restaurant cookie",
    "restaurant dessert",
    "restaurant dish",
    "restaurant fish",
    "restaurant food",
    "restaurant fruit",
    "restaurant meal",
    "restaurant milk",
    "restaurant pasta",
    "restaurant pizza",
    "restaurant pork",
    "restaurant salad",
    "restaurant sandwich",
    "restaurant snack",
    "restaurant soup",
    "restaurant sushi",
    "restaurant taco",
    "restaurant vegetable",
    "road trip",
    "rock band",
    "run bike",
    "run book",
    "run car",
    "run computer",
    "run food",
    "run game",
    "run guitar",
    "run movie",
    "run music",
    "run phone",
    "run piano",
    "run radio",
    "run sport",
    "run television",
    "rush hour",
    "salty beef",
    "salty bread",
    "salty burger",
    "salty cake",
    "salty cheese",
    "salty chicken",
    "salty cookie",
    "salty dessert",
    "salty dish",
    "salty fish",
    "salty food",
    "salty fruit",
    "salty meal",
    "salty milk",
    "salty pasta",
    "salty pizza",
    "salty pork",
    "salty salad",
    "salty sandwich",
    "salty snack",
    "salty soup",
    "salty sushi",
    "salty taco",
    "salty vegetable",
    "school city",
    "sea food",
    "shopping grocery",
    "shopping mall",
    "show for family",
    "show time",
    "sing bike",
    "sing book",
    "sing car",
    "sing computer",
    "sing food",
    "sing game",
    "sing guitar",
    "sing movie",
    "sing music",
    "sing phone",
    "sing piano",
    "sing radio",
    "sing sport",
    "sing television",
    "ski trip",
    "slam dunk",
    "slow beef",
    "slow bread",
    "slow burger",
    "slow cake",
    "slow cheese",
    "slow chicken",
    "slow cookie",
    "slow dessert",
    "slow dish",
    "slow fish",
    "slow food",
    "slow fruit",
    "slow meal",
    "slow milk",
    "slow pasta",
    "slow pizza",
    "slow pork",
    "slow salad",
    "slow sandwich",
    "slow snack",
    "slow soup",
    "slow sushi",
    "slow taco",
    "slow vegetable",
    "small airport",
    "small avenue",
    "small bar",
    "small building",
    "small cafe",
    "small center",
    "small hospital",
    "small house",
    "small library",
    "small mall",
    "small museum",
    "small office",
    "small park",
    "small restaurant",
    "small school",
    "small shop",
    "small square",
    "small station",
    "small store",
    "small street",
    "small theater",
    "smart application",
    "smart camera",
    "smart computer",
    "smart device",
    "smart gadget",
    "smart machine",
    "smart mobile",
    "smart network",
    "smart phone",
    "smart player",
    "smart service",
    "smart software",
    "smart system",
    "smart tool",
    "social media",
    "solar application",
    "solar camera",
    "solar computer",
    "solar device",
    "solar gadget",
    "solar machine",
    "solar network",
    "solar phone",
    "solar player",
    "solar service",
    "solar software",
    "solar system",
    "solar tool",
    "sour beef",
    "sour bread",
    "sour burger",
    "sour cake",
    "sour cheese",
    "sour chicken",
    "sour cookie",
    "sour dessert",
    "sour dish",
    "sour fish",
    "sour food",
    "sour fruit",
    "sour meal",
    "sour milk",
    "sour pasta",
    "sour pizza",
    "sour pork",
    "sour salad",
    "sour sandwich",
    "sour snack",
    "sour soup",
    "sour sushi",
    "sour taco",
    "sour vegetable",
    "spicy beef",
    "spicy bread",
    "spicy burger",
    "spicy cake",
    "spicy cheese",
    "spicy chicken",
    "spicy cookie",
    "spicy dessert",
    "spicy dish",
    "spicy fish",
    "spicy food",
    "spicy fruit",
    "spicy meal",
    "spicy milk",
    "spicy pasta",
    "spicy pizza",
    "spicy pork",
    "spicy salad",
    "spicy sandwich",
    "spicy snack",
    "spicy soup",
    "spicy sushi",
    "spicy taco",
    "spicy vegetable",
    "store mall",
    "streaming service",
    "study bike",
    "study book",
    "study car",
    "study computer",
    "study food",
    "study game",
    "study guitar",
    "study movie",
    "study music",
    "study phone",
    "study piano",
    "study radio",
    "study sport",
    "study television",
    "sweet beef",
    "sweet bread",
    "sweet burger",
    "sweet cake",
    "sweet cheese",
    "sweet chicken",
    "sweet cookie",
    "sweet dessert",
    "sweet dish",
    "sweet fish",
    "sweet food",
    "sweet fruit",
    "sweet meal",
    "sweet milk",
    "sweet pasta",
    "sweet pizza",
    "sweet pork",
    "sweet salad",
    "sweet sandwich",
    "sweet snack",
    "sweet soup",
    "sweet sushi",
    "sweet taco",
    "sweet vegetable",
    "swim bike",
    "swim book",
    "swim car",
    "swim computer",
    "swim food",
    "swim game",
    "swim guitar",
    "swim movie",
    "swim music",
    "swim phone",
    "swim piano",
    "swim radio",
    "swim sport",
    "swim television",
    "tablet computer",
    "theme park",
    "tool for cooking",
    "touch down",
    "toy store",
    "train station",
    "uptown airport",
    "uptown avenue",
    "uptown bar",
    "uptown building",
    "uptown cafe",
    "uptown center",
    "uptown hospital",
    "uptown house",
    "uptown library",
    "uptown mall",
    "uptown museum",
    "uptown office",
    "uptown park",
    "uptown restaurant",
    "uptown school",
    "uptown shop",
    "uptown square",
    "uptown station",
    "uptown store",
    "uptown street",
    "uptown theater",
    "video board",
    "video game",
    "walk bike",
    "walk book",
    "walk car",
    "walk computer",
    "walk food",
    "walk game",
    "walk guitar",
    "walk movie",
    "walk music",
    "walk phone",
    "walk piano",
    "walk radio",
    "walk sport",
    "walk television",
    "watch bike",
    "watch book",
    "watch car",
    "watch computer",
    "watch food",
    "watch game",
    "watch guitar",
    "watch movie",
    "watch music",
    "watch phone",
    "watch piano",
    "watch radio",
    "watch sport",
    "watch television",
    "water park",
    "wedding party",
    "wireless application",
    "wireless camera",
    "wireless computer",
    "wireless device",
    "wireless gadget",
    "wireless machine",
    "wireless network",
    "wireless phone",
    "wireless player",
    "wireless service",
    "wireless software",
    "wireless system",
    "wireless tool",
    "work bike",
    "work book",
    "work car",
    "work computer",
    "work food",
    "work game",
    "work guitar",
    "work movie",
    "work music",
    "work phone",
    "work piano",
    "work radio",
    "work sport",
    "work television",
    "write bike",
    "write book",
    "write car",
    "write computer",
    "write food",
    "write game",
    "write guitar",
    "write movie",
    "write music",
    "write phone",
    "write piano",
    "write radio",
    "write sport",
    "write television"
  ],
  "byCategory": {
    "curated": [
      "afternoon tea",
      "amusement park",
      "app for music",
      "bath room",
      "bed room",
      "bed time",
      "birthday party",
      "block party",
      "board game",
      "book on shelf",
      "book store",
      "break time",
      "bus station",
      "bus train",
      "business trip",
      "cable television",
      "camping trip",
      "car in garage",
      "car with radio",
      "cell phone",
      "class room",
      "coffee shop",
      "comfort food",
      "credit card",
      "department store",
      "desktop computer",
      "dining room",
      "dinner party",
      "family trip",
      "field goal",
      "fire station",
      "food on table",
      "free throw",
      "french fries",
      "game console",
      "game for kids",
      "game show",
      "gas station",
      "grocery store",
      "happy hour",
      "health food",
      "high school",
      "home run",
      "hot dog",
      "house in suburbs",
      "house party",
      "house with pool",
      "ice cream",
      "laptop computer",
      "laptop with battery",
      "living room",
      "lunch break",
      "mass media",
      "meal time",
      "morning afternoon",
      "morning coffee",
      "movie theater",
      "music store",
      "national park",
      "news media",
      "parking lot",
      "phone computer",
      "phone with camera",
      "police station",
      "pool party",
      "pop music",
      "post office",
      "prime time",
      "reality show",
      "road trip",
      "rock band",
      "rush hour",
      "school city",
      "sea food",
      "shopping grocery",
      "shopping mall",
      "show for family",
      "show time",
      "ski trip",
      "slam dunk",
      "smart mobile",
      "social media",
      "store mall",
      "streaming service",
      "tablet computer",
      "theme park",
      "tool for cooking",
      "touch down",
      "toy store",
      "train station",
      "video board",
      "video game",
      "water park",
      "wedding party"
    ],
    "food": [
      "american beef",
      "american bread",
      "american burger",
      "american cake",
      "american cheese",
      "american chicken",
      "american cookie",
      "american dessert",
      "american dish",
      "american fish",
      "american food",
      "american fruit",
      "american meal",
      "american milk",
      "american pasta",
      "american pizza",
      "american pork",
      "american salad",
      "american sandwich",
      "american snack",
      "american soup",
      "american sushi",
      "american taco",
      "american vegetable",
      "chinese beef",
      "chinese bread",
      "chinese burger",
      "chinese cake",
      "chinese cheese",
      "chinese chicken",
      "chinese cookie",
      "chinese dessert",
      "chinese dish",
      "chinese fish",
      "chinese food",
      "chinese fruit",
      "chinese meal",
      "chinese milk",
      "chinese pasta",
      "chinese pizza",
      "chinese pork",
      "chinese salad",
      "chinese sandwich",
      "chinese snack",
      "chinese soup",
      "chinese sushi",
      "chinese taco",
      "chinese vegetable",
      "cold beef",
      "cold bread",
      "cold burger",
      "cold cake",
      "cold cheese",
      "cold chicken",
      "cold cookie",
      "cold dessert",
      "cold dish",
      "cold fish",
      "cold food",
      "cold fruit",
      "cold meal",
      "cold milk",
      "cold pasta",
      "cold pizza",
      "cold pork",
      "cold salad",
      "cold sandwich",
      "cold snack",
      "cold soup",
      "cold sushi",
      "cold taco",
      "cold vegetable",
      "fast beef",
      "fast bread",
      "fast burger",
      "fast cake",
      "fast cheese",
      "fast chicken",
      "fast cookie",
      "fast dessert",
      "fast dish",
      "fast fish",
      "fast food",
      "fast fruit",
      "fast meal",
      "fast milk",
      "fast pasta",
      "fast pizza",
      "fast pork",
      "fast salad",
      "fast sandwich",
      "fast snack",
      "fast soup",
      "fast sushi",
      "fast taco",
      "fast vegetable",
      "french beef",
      "french bread",
      "french burger",
      "french cake",
      "french cheese",
      "french chicken",
      "french cookie",
      "french dessert",
      "french dish",
      "french fish",
      "french food",
      "french fruit",
      "french meal",
      "french milk",
      "french pasta",
      "french pizza",
      "french pork",
      "french salad",
      "french sandwich",
      "french snack",
      "french soup",
      "french sushi",
      "french taco",
      "french vegetable",
      "fresh beef",
      "fresh bread",
      "fresh burger",
      "fresh cake",
      "fresh cheese",
      "fresh chicken",
      "fresh cookie",
      "fresh dessert",
      "fresh dish",
      "fresh fish",
      "fresh food",
      "fresh fruit",
      "fresh meal",
      "fresh milk",
      "fresh pasta",
      "fresh pizza",
      "fresh pork",
      "fresh salad",
      "fresh sandwich",
      "fresh snack",
      "fresh soup",
      "fresh sushi",
      "fresh taco",
      "fresh vegetable",
      "frozen beef",
      "frozen bread",
      "frozen burger",
      "frozen cake",
      "frozen cheese",
      "frozen chicken",
      "frozen cookie",
      "frozen dessert",
      "frozen dish",
      "frozen fish",
      "frozen food",
      "frozen fruit",
      "frozen meal",
      "frozen milk",
      "frozen pasta",
      "frozen pizza",
      "frozen pork",
      "frozen salad",
      "frozen sandwich",
      "frozen snack",
      "frozen soup",
      "frozen sushi",
      "frozen taco",
      "frozen vegetable",
      "healthy beef",
      "healthy bread",
      "healthy burger",
      "healthy cake",
      "healthy cheese",
      "healthy chicken",
      "healthy cookie",
      "healthy dessert",
      "healthy dish",
      "healthy fish",
      "healthy food",
      "healthy fruit",
      "healthy meal",
      "healthy milk",
      "healthy pasta",
      "healthy pizza",
      "healthy pork",
      "healthy salad",
      "healthy sandwich",
      "healthy snack",
      "healthy soup",
      "healthy sushi",
      "healthy taco",
      "healthy vegetable",
      "home beef",
      "home bread",
      "home burger",
      "home cake",
      "home cheese",
      "home chicken",
      "home cookie",
      "home dessert",
      "home dish",
      "home fish",
      "home food",
      "home fruit",
      "home meal",
      "home milk",
      "home pasta",
      "home pizza",
      "home pork",
      "home salad",
      "home sandwich",
      "home snack",
      "home soup",
      "home sushi",
      "home taco",
      "home vegetable",
      "hot beef",
      "hot bread",
      "hot burger",
      "hot cake",
      "hot cheese",
      "hot chicken",
      "hot cookie",
      "hot dessert",
      "hot dish",
      "hot fish",
      "hot food",
      "hot fruit",
      "hot meal",
      "hot milk",
      "hot pasta",
      "hot pizza",
      "hot pork",
      "hot salad",
      "hot sandwich",
      "hot snack",
      "hot soup",
      "hot sushi",
      "hot taco",
      "hot vegetable",
      "indian beef",
      "indian bread",
      "indian burger",
      "indian cake",
      "indian cheese",
      "indian chicken",
      "indian cookie",
      "indian dessert",
      "indian dish",
      "indian fish",
      "indian food",
      "indian fruit",
      "indian meal",
      "indian milk",
      "indian pasta",
      "indian pizza",
      "indian pork",
      "indian salad",
      "indian sandwich",
      "indian snack",
      "indian soup",
      "indian sushi",
      "indian taco",
      "indian vegetable",
      "italian beef",
      "italian bread",
      "italian burger",
      "italian cake",
      "italian cheese",
      "italian chicken",
      "italian cookie",
      "italian dessert",
      "italian dish",
      "italian fish",
      "italian food",
      "italian fruit",
      "italian meal",
      "italian milk",
      "italian pasta",
      "italian pizza",
      "italian pork",
      "italian salad",
      "italian sandwich",
      "italian snack",
      "italian soup",
      "italian sushi",
      "italian taco",
      "italian vegetable",
      "junk beef",
      "junk bread",
      "junk burger",
      "junk cake",
      "junk cheese",
      "junk chicken",
      "junk cookie",
      "junk dessert",
      "junk dish",
      "junk fish",
      "junk food",
      "junk fruit",
      "junk meal",
      "junk milk",
      "junk pasta",
      "junk pizza",
      "junk pork",
      "junk salad",
      "junk sandwich",
      "junk snack",
      "junk soup",
      "junk sushi",
      "junk taco",
      "junk vegetable",
      "mexican beef",
      "mexican bread",
      "mexican burger",
      "mexican cake",
      "mexican cheese",
      "mexican chicken",
      "mexican cookie",
      "mexican dessert",
      "mexican dish",
      "mexican fish",
      "mexican food",
      "mexican fruit",
      "mexican meal",
      "mexican milk",
      "mexican pasta",
      "mexican pizza",
      "mexican pork",
      "mexican salad",
      "mexican sandwich",
      "mexican snack",
      "mexican soup",
      "mexican sushi",
      "mexican taco",
      "mexican vegetable",
      "organic beef",
      "organic bread",
      "organic burger",
      "organic cake",
      "organic cheese",
      "organic chicken",
      "organic cookie",
      "organic dessert",
      "organic dish",
      "organic fish",
      "organic food",
      "organic fruit",
      "organic meal",
      "organic milk",
      "organic pasta",
      "organic pizza",
      "organic pork",
      "organic salad",
      "organic sandwich",
      "organic snack",
      "organic soup",
      "organic sushi",
      "organic taco",
      "organic vegetable",
      "restaurant beef",
      "restaurant bread",
      "restaurant burger",
      "restaurant cake",
      "restaurant cheese",
      "restaurant chicken",
      "restaurant cookie",
      "restaurant dessert",
      "restaurant dish",
      "restaurant fish",
      "restaurant food",
      "restaurant fruit",
      "restaurant meal",
      "restaurant milk",
      "restaurant pasta",
      "restaurant pizza",
      "restaurant pork",
      "restaurant salad",
      "restaurant sandwich",
      "restaurant snack",
      "restaurant soup",
      "restaurant sushi",
      "restaurant taco",
      "restaurant vegetable",
      "salty beef",
      "salty bread",
      "salty burger",
      "salty cake",
      "salty cheese",
      "salty chicken",
      "salty cookie",
      "salty dessert",
      "salty dish",
      "salty fish",
      "salty food",
      "salty fruit",
      "salty meal",
      "salty milk",
      "salty pasta",
      "salty pizza",
      "salty pork",
      "salty salad",
      "salty sandwich",
      "salty snack",
      "salty soup",
      "salty sushi",
      "salty taco",
      "salty vegetable",
      "slow beef",
      "slow bread",
      "slow burger",
      "slow cake",
      "slow cheese",
      "slow chicken",
      "slow cookie",
      "slow dessert",
      "slow dish",
      "slow fish",
      "slow food",
      "slow fruit",
      "slow meal",
      "slow milk",
      "slow pasta",
      "slow pizza",
      "slow pork",
      "slow salad",
      "slow sandwich",
      "slow snack",
      "slow soup",
      "slow sushi",
      "slow taco",
      "slow vegetable",
      "sour beef",
      "sour bread",
      "sour burger",
      "sour cake",
      "sour cheese",
      "sour chicken",
      "sour cookie",
      "sour dessert",
      "sour dish",
      "sour fish",
      "sour food",
      "sour fruit",
      "sour meal",
      "sour milk",
      "sour pasta",
      "sour pizza",
      "sour pork",
      "sour salad",
      "sour sandwich",
      "sour snack",
      "sour soup",
      "sour sushi",
      "sour taco",
      "sour vegetable",
      "spicy beef",
      "spicy bread",
      "spicy burger",
      "spicy cake",
      "spicy cheese",
      "spicy chicken",
      "spicy cookie",
      "spicy dessert",
      "spicy dish",
      "spicy fish",
      "spicy food",
      "spicy fruit",
      "spicy meal",
      "spicy milk",
      "spicy pasta",
      "spicy pizza",
      "spicy pork",
      "spicy salad",
      "spicy sandwich",
      "spicy snack",
      "spicy soup",
      "spicy sushi",
      "spicy taco",
      "spicy vegetable",
      "sweet beef",
      "sweet bread",
      "sweet burger",
      "sweet cake",
      "sweet cheese",
      "sweet chicken",
      "sweet cookie",
      "sweet dessert",
      "sweet dish",
      "sweet fish",
      "sweet food",
      "sweet fruit",
      "sweet meal",
      "sweet milk",
      "sweet pasta",
      "sweet pizza",
      "sweet pork",
      "sweet salad",
      "sweet sandwich",
      "sweet snack",
      "sweet soup",
      "sweet sushi",
      "sweet taco",
      "sweet vegetable"
    ],
    "object": [
      "automatic application",
      "automatic camera",
      "automatic computer",
      "automatic device",
      "automatic gadget",
      "automatic machine",
      "automatic network",
      "automatic phone",
      "automatic player",
      "automatic service",
      "automatic software",
      "automatic system",
      "automatic tool",
      "battery application",
      "battery camera",
      "battery computer",
      "battery device",
      "battery gadget",
      "battery machine",
      "battery network",
      "battery phone",
      "battery player",
      "battery service",
      "battery software",
      "battery system",
      "battery tool",
      "digital application",
      "digital camera",
      "digital computer",
      "digital device",
      "digital gadget",
      "digital machine",
      "digital network",
      "digital phone",
      "digital player",
      "digital service",
      "digital software",
      "digital system",
      "digital tool",
      "electric application",
      "electric camera",
      "electric computer",
      "electric device",
      "electric gadget",
      "electric machine",
      "electric network",
      "electric phone",
      "electric player",
      "electric service",
      "electric software",
      "electric system",
      "electric tool",
      "electronic application",
      "electronic camera",
      "electronic computer",
      "electronic device",
      "electronic gadget",
      "electronic machine",
      "electronic network",
      "electronic phone",
      "electronic player",
      "electronic service",
      "electronic software",
      "electronic system",
      "electronic tool",
      "manual application",
      "manual camera",
      "manual computer",
      "manual device",
      "manual gadget",
      "manual machine",
      "manual network",
      "manual phone",
      "manual player",
      "manual service",
      "manual software",
      "manual system",
      "manual tool",
      "mobile application",
      "mobile camera",
      "mobile computer",
      "mobile device",
      "mobile gadget",
      "mobile machine",
      "mobile network",
      "mobile phone",
      "mobile player",
      "mobile service",
      "mobile software",
      "mobile system",
      "mobile tool",
      "portable application",
      "portable camera",
      "portable computer",
      "portable device",
      "portable gadget",
      "portable machine",
      "portable network",
      "portable phone",
      "portable player",
      "portable service",
      "portable software",
      "portable system",
      "portable tool",
      "rechargeable application",
      "rechargeable camera",
      "rechargeable computer",
      "rechargeable device",
      "rechargeable gadget",
      "rechargeable machine",
      "rechargeable network",
      "rechargeable phone",
      "rechargeable player",
      "rechargeable service",
      "rechargeable software",
      "rechargeable system",
      "rechargeable tool",
      "smart application",
      "smart camera",
      "smart computer",
      "smart device",
      "smart gadget",
      "smart machine",
      "smart network",
      "smart phone",
      "smart player",
      "smart service",
      "smart software",
      "smart system",
      "smart tool",
      "solar application",
      "solar camera",
      "solar computer",
      "solar device",
      "solar gadget",
      "solar machine",
      "solar network",
      "solar phone",
      "solar player",
      "solar service",
      "solar software",
      "solar system",
      "solar tool",
      "wireless application",
      "wireless camera",
      "wireless computer",
      "wireless device",
      "wireless gadget",
      "wireless machine",
      "wireless network",
      "wireless phone",
      "wireless player",
      "wireless service",
      "wireless software",
      "wireless system",
      "wireless tool"
    ],
    "place": [
      "big airport",
      "big avenue",
      "big bar",
      "big building",
      "big cafe",
      "big center",
      "big hospital",
      "big house",
      "big library",
      "big mall",
      "big museum",
      "big office",
      "big park",
      "big restaurant",
      "big school",
      "big shop",
      "big square",
      "big station",
      "big store",
      "big street",
      "big theater",
      "busy airport",
      "busy avenue",
      "busy bar",
      "busy building",
      "busy cafe",
      "busy center",
      "busy hospital",
      "busy house",
      "busy library",
      "busy mall",
      "busy museum",
      "busy office",
      "busy park",
      "busy restaurant",
      "busy school",
      "busy shop",
      "busy square",
      "busy station",
      "busy store",
      "busy street",
      "busy theater",
      "downtown airport",
      "downtown avenue",
      "downtown bar",
      "downtown building",
      "downtown cafe",
      "downtown center",
      "downtown hospital",
      "downtown house",
      "downtown library",
      "downtown mall",
      "downtown museum",
      "downtown office",
      "downtown park",
      "downtown restaurant",
      "downtown school",
      "downtown shop",
      "downtown square",
      "downtown station",
      "downtown store",
      "downtown street",
      "downtown theater",
      "historic airport",
      "historic avenue",
      "historic bar",
      "historic building",
      "historic cafe",
      "historic center",
      "historic hospital",
      "historic house",
      "historic library",
      "historic mall",
      "historic museum",
      "historic office",
      "historic park",
      "historic restaurant",
      "historic school",
      "historic shop",
      "historic square",
      "historic station",
      "historic store",
      "historic street",
      "historic theater",
      "indoor airport",
      "indoor avenue",
      "indoor bar",
      "indoor building",
      "indoor cafe",
      "indoor center",
      "indoor hospital",
      "indoor house",
      "indoor library",
      "indoor mall",
      "indoor museum",
      "indoor office",
      "indoor park",
      "indoor restaurant",
      "indoor school",
      "indoor shop",
      "indoor square",
      "indoor station",
      "indoor store",
      "indoor street",
      "indoor theater",
      "local airport",
      "local avenue",
      "local bar",
      "local building",
      "local cafe",
      "local center",
      "local hospital",
      "local house",
      "local library",
      "local mall",
      "local museum",
      "local office",
      "local park",
      "local restaurant",
      "local school",
      "local shop",
      "local square",
      "local station",
      "local store",
      "local street",
      "local theater",
      "modern airport",
      "modern avenue",
      "modern bar",
      "modern building",
      "modern cafe",
      "modern center",
      "modern hospital",
      "modern house",
      "modern library",
      "modern mall",
      "modern museum",
      "modern office",
      "modern park",
      "modern restaurant",
      "modern school",
      "modern shop",
      "modern square",
      "modern station",
      "modern store",
      "modern street",
      "modern theater",
      "new airport",
      "new avenue",
      "new bar",
      "new building",
      "new cafe",
      "new center",
      "new hospital",
      "new house",
      "new library",
      "new mall",
      "new museum",
      "new office",
      "new park",
      "new restaurant",
      "new school",
      "new shop",
      "new square",
      "new station",
      "new store",
      "new street",
      "new theater",
      "old airport",
      "old avenue",
      "old bar",
      "old building",
      "old cafe",
      "old center",
      "old hospital",
      "old house",
      "old library",
      "old mall",
      "old museum",
      "old office",
      "old park",
      "old restaurant",
      "old school",
      "old shop",
      "old square",
      "old station",
      "old store",
      "old street",
      "old theater",
      "outdoor airport",
      "outdoor avenue",
      "outdoor bar",
      "outdoor building",
      "outdoor cafe",
      "outdoor center",
      "outdoor hospital",
      "outdoor house",
      "outdoor library",
      "outdoor mall",
      "outdoor museum",
      "outdoor office",
      "outdoor park",
      "outdoor restaurant",
      "outdoor school",
      "outdoor shop",
      "outdoor square",
      "outdoor station",
      "outdoor store",
      "outdoor street",
      "outdoor theater",
      "private airport",
      "private avenue",
      "private bar",
      "private building",
      "private cafe",
      "private center",
      "private hospital",
      "private house",
      "private library",
      "private mall",
      "private museum",
      "private office",
      "private park",
      "private restaurant",
      "private school",
      "private shop",
      "private square",
      "private station",
      "private store",
      "private street",
      "private theater",
      "public airport",
      "public avenue",
      "public bar",
      "public building",
      "public cafe",
      "public center",
      "public hospital",
      "public house",
      "public library",
      "public mall",
      "public museum",
      "public office",
      "public park",
      "public restaurant",
      "public school",
      "public shop",
      "public square",
      "public station",
      "public store",
      "public street",
      "public theater",
      "quiet airport",
      "quiet avenue",
      "quiet bar",
      "quiet building",
      "quiet cafe",
      "quiet center",
      "quiet hospital",
      "quiet house",
      "quiet library",
      "quiet mall",
      "quiet museum",
      "quiet office",
      "quiet park",
      "quiet restaurant",
      "quiet school",
      "quiet shop",
      "quiet square",
      "quiet station",
      "quiet store",
      "quiet street",
      "quiet theater",
      "small airport",
      "small avenue",
      "small bar",
      "small building",
      "small cafe",
      "small center",
      "small hospital",
      "small house",
      "small library",
      "small mall",
      "small museum",
      "small office",
      "small park",
      "small restaurant",
      "small school",
      "small shop",
      "small square",
      "small station",
      "small store",
      "small street",
      "small theater",
      "uptown airport",
      "uptown avenue",
      "uptown bar",
      "uptown building",
      "uptown cafe",
      "uptown center",
      "uptown hospital",
      "uptown house",
      "uptown library",
      "uptown mall",
      "uptown museum",
      "uptown office",
      "uptown park",
      "uptown restaurant",
      "uptown school",
      "uptown shop",
      "uptown square",
      "uptown station",
      "uptown store",
      "uptown street",
      "uptown theater"
    ],
    "activity": [
      "cook bike",
      "cook book",
      "cook car",
      "cook computer",
      "cook food",
      "cook game",
      "cook guitar",
      "cook movie",
      "cook music",
      "cook phone",
      "cook piano",
      "cook radio",
      "cook sport",
      "cook television",
      "dance bike",
      "dance book",
      "dance car",
      "dance computer",
      "dance food",
      "dance game",
      "dance guitar",
      "dance movie",
      "dance music",
      "dance phone",
      "dance piano",
      "dance radio",
      "dance sport",
      "dance television",
      "drink bike",
      "drink book",
      "drink car",
      "drink computer",
      "drink food",
      "drink game",
      "drink guitar",
      "drink movie",
      "drink music",
      "drink phone",
      "drink piano",
      "drink radio",
      "drink sport",
      "drink television",
      "drive bike",
      "drive book",
      "drive car",
      "drive computer",
      "drive food",
      "drive game",
      "drive guitar",
      "drive movie",
      "drive music",
      "drive phone",
      "drive piano",
      "drive radio",
      "drive sport",
      "drive television",
      "eat bike",
      "eat book",
      "eat car",
      "eat computer",
      "eat food",
      "eat game",
      "eat guitar",
      "eat movie",
      "eat music",
      "eat phone",
      "eat piano",
      "eat radio",
      "eat sport",
      "eat television",
      "listen bike",
      "listen book",
      "listen car",
      "listen computer",
      "listen food",
      "listen game",
      "listen guitar",
      "listen movie",
      "listen music",
      "listen phone",
      "listen piano",
      "listen radio",
      "listen sport",
      "listen television",
      "play bike",
      "play book",
      "play car",
      "play computer",
      "play food",
      "play game",
      "play guitar",
      "play movie",
      "play music",
      "play phone",
      "play piano",
      "play radio",
      "play sport",
      "play television",
      "read bike",
      "read book",
      "read car",
      "read computer",
      "read food",
      "read game",
      "read guitar",
      "read movie",
      "read music",
      "read phone",
      "read piano",
      "read radio",
      "read sport",
      "read television",
      "run bike",
      "run book",
      "run car",
      "run computer",
      "run food",
      "run game",
      "run guitar",
      "run movie",
      "run music",
      "run phone",
      "run piano",
      "run radio",
      "run sport",
      "run television",
      "sing bike",
      "sing book",
      "sing car",
      "sing computer",
      "sing food",
      "sing game",
      "sing guitar",
      "sing movie",
      "sing music",
      "sing phone",
      "sing piano",
      "sing radio",
      "sing sport",
      "sing television",
      "study bike",
      "study book",
      "study car",
      "study computer",
      "study food",
      "study game",
      "study guitar",
      "study movie",
      "study music",
      "study phone",
      "study piano",
      "study radio",
      "study sport",
      "study television",
      "swim bike",
      "swim book",
      "swim car",
      "swim computer",
      "swim food",
      "swim game",
      "swim guitar",
      "swim movie",
      "swim music",
      "swim phone",
      "swim piano",
      "swim radio",
      "swim sport",
      "swim television",
      "walk bike",
      "walk book",
      "walk car",
      "walk computer",
      "walk food",
      "walk game",
      "walk guitar",
      "walk movie",
      "walk music",
      "walk phone",
      "walk piano",
      "walk radio",
      "walk sport",
      "walk television",
      "watch bike",
      "watch book",
      "watch car",
      "watch computer",
      "watch food",
      "watch game",
      "watch guitar",
      "watch movie",
      "watch music",
      "watch phone",
      "watch piano",
      "watch radio",
      "watch sport",
      "watch television",
      "work bike",
      "work book",
      "work car",
      "work computer",
      "work food",
      "work game",
      "work guitar",
      "work movie",
      "work music",
      "work phone",
      "work piano",
      "work radio",
      "work sport",
      "work television",
      "write bike",
      "write book",
      "write car",
      "write computer",
      "write food",
      "write game",
      "write guitar",
      "write movie",
      "write music",
      "write phone",
      "write piano",
      "write radio",
      "write sport",
      "write television"
    ]
  },
  "categories": {
    "curated": 94,
    "food": 504,
    "object": 156,
    "place": 315,
    "activity": 224
  }
}